image_functions-0.1.12.dist-info/licenses/LICENSE
imfun/__init__.py
imfun/__main__.py
image_functions-0.1.12.dist-info/METADATA
image_functions-0.1.12.dist-info/WHEEL
image_functions-0.1.12.dist-info/top_level.txt
image_functions-0.1.12.dist-info/RECORD
