Metadata-Version: 2.4
Name: image-functions
Version: 0.1.12
Summary: Image Processing Functions
Author-email: Marlon Rodrigues Garcia <marlon.garcia@unesp.br>
License-Expression: MIT
Project-URL: Homepage, https://github.com/MarlonGarcia/imfun
Keywords: image processing,digital image,image functions,machine learning data preparation,artificial intelligence data preparation
Classifier: Programming Language :: Python
Classifier: Programming Language :: Python :: 3
Requires-Python: >=3.7
License-File: LICENSE
Requires-Dist: numpy
Requires-Dist: opencv-contrib-python
Requires-Dist: matplotlib
Requires-Dist: scipy
Requires-Dist: pandas
Requires-Dist: tifffile
Requires-Dist: scikit-image
Requires-Dist: natsort
Dynamic: license-file
